ray_appengine/__init__.py
ray_appengine/all.py
ray_appengine-0.2.0.dist-info/DESCRIPTION.rst
ray_appengine-0.2.0.dist-info/METADATA
ray_appengine-0.2.0.dist-info/RECORD
ray_appengine-0.2.0.dist-info/WHEEL
ray_appengine-0.2.0.dist-info/entry_points.txt
ray_appengine-0.2.0.dist-info/metadata.json
ray_appengine-0.2.0.dist-info/top_level.txt
