Metadata-Version: 2.0
Name: ray-appengine
Version: 0.2.0
Summary:     Ray is a framework that helps you to deliver
Home-page: http://github.com/felipevolpone/ray
Author: Felipe Volpone
Author-email: felipevolpone@gmail.com
License: MIT
Keywords: appengine framework ray api rest google
Platform: UNKNOWN
Classifier: Development Status :: 3 - Alpha
Classifier: Topic :: Utilities
